pymatcher_utils/__init__.py
pymatcher_utils/array.py
pymatcher_utils/dict.py
pymatcher_utils/exception.py
pymatcher_utils/matcher.py
pymatcher_utils/method.py
pymatcher_utils/property.py
pymatcher_utils/py.typed
pymatcherutil-0.1.2.dist-info/licenses/LICENSE
pymatcherutil-0.1.2.dist-info/METADATA
pymatcherutil-0.1.2.dist-info/WHEEL
pymatcherutil-0.1.2.dist-info/top_level.txt
pymatcherutil-0.1.2.dist-info/RECORD
