Metadata-Version: 2.4
Name: PyMatcherUtil
Version: 0.1.2
Summary: Python matcher utility for enhancing assertion in unit tests
Author-email: Akito Nozaki <akito@tanoshi.net>
Maintainer-email: Akito Nozaki <akito@tanoshi.net>
Requires-Python: >=3.9
License-File: LICENSE
Provides-Extra: dev
Requires-Dist: pylint~=3.3.1; extra == "dev"
Requires-Dist: mypy~=1.13.0; extra == "dev"
Requires-Dist: pytest~=8.3.3; extra == "dev"
Requires-Dist: pytest-cov~=6.0.0; extra == "dev"
Requires-Dist: black~=24.10.0; extra == "dev"
Requires-Dist: pydocstyle[toml]~=6.3.0; extra == "dev"
Requires-Dist: docformatter~=1.7.5; extra == "dev"
Dynamic: license-file
